<annotation>
	<folder>images</folder>
	<filename>outdoor_daytime_20m_gasoline_CCD_001_frames_18.jpg</filename>
	<path>D:\Detect\Main_folder_data_labeled\images\outdoor_daytime_20m_gasoline_CCD_001_frames_18.jpg</path>
	<source>
		<database>Unknown</database>
	</source>
	<size>
		<width>320</width>
		<height>240</height>
		<depth>3</depth>
	</size>
	<segmented>0</segmented>
	<object>
		<name>fire</name>
		<pose>Unspecified</pose>
		<truncated>0</truncated>
		<difficult>0</difficult>
		<bndbox>
			<xmin>112</xmin>
			<ymin>115</ymin>
			<xmax>133</xmax>
			<ymax>153</ymax>
		</bndbox>
	</object>
</annotation>
